setup.py
netforce_test/__init__.py
netforce_test.egg-info/PKG-INFO
netforce_test.egg-info/SOURCES.txt
netforce_test.egg-info/dependency_links.txt
netforce_test.egg-info/not-zip-safe
netforce_test.egg-info/top_level.txt